ibm_ai_openscale/__init__.py
ibm_ai_openscale/applications.py
ibm_ai_openscale/bindings.py
ibm_ai_openscale/client.py
ibm_ai_openscale/client_4_icp.py
ibm_ai_openscale/clients_manager.py
ibm_ai_openscale/data_mart.py
ibm_ai_openscale/monitors.py
ibm_ai_openscale/subscriptions.py
ibm_ai_openscale/base_classes/__init__.py
ibm_ai_openscale/base_classes/artifact.py
ibm_ai_openscale/base_classes/metanames.py
ibm_ai_openscale/base_classes/source_deployment.py
ibm_ai_openscale/base_classes/tables.py
ibm_ai_openscale/base_classes/assets/__init__.py
ibm_ai_openscale/base_classes/assets/asset.py
ibm_ai_openscale/base_classes/assets/known_service_asset.py
ibm_ai_openscale/base_classes/assets/properties.py
ibm_ai_openscale/base_classes/client/__init__.py
ibm_ai_openscale/base_classes/client/client.py
ibm_ai_openscale/base_classes/clients/__init__.py
ibm_ai_openscale/base_classes/clients/client.py
ibm_ai_openscale/base_classes/clients/client_with_ml_gateway_support.py
ibm_ai_openscale/base_classes/clients/known_service_client.py
ibm_ai_openscale/base_classes/configuration/__init__.py
ibm_ai_openscale/base_classes/configuration/custom_metrics_viewer.py
ibm_ai_openscale/base_classes/configuration/data_distribution.py
ibm_ai_openscale/base_classes/configuration/drift_monitoring.py
ibm_ai_openscale/base_classes/configuration/explainability.py
ibm_ai_openscale/base_classes/configuration/fairness_monitoring.py
ibm_ai_openscale/base_classes/configuration/feedback_logging.py
ibm_ai_openscale/base_classes/configuration/metrics_viewer.py
ibm_ai_openscale/base_classes/configuration/monitoring.py
ibm_ai_openscale/base_classes/configuration/payload_logging.py
ibm_ai_openscale/base_classes/configuration/performance_monitoring.py
ibm_ai_openscale/base_classes/configuration/quality_monitoring.py
ibm_ai_openscale/base_classes/configuration/table_from_rest_api_viewer.py
ibm_ai_openscale/base_classes/instances/__init__.py
ibm_ai_openscale/base_classes/instances/ai_instance.py
ibm_ai_openscale-2.2.1.dist-info/LICENSE.txt
ibm_ai_openscale-2.2.1.dist-info/METADATA
ibm_ai_openscale-2.2.1.dist-info/WHEEL
ibm_ai_openscale-2.2.1.dist-info/top_level.txt
ibm_ai_openscale-2.2.1.dist-info/RECORD
