Metadata-Version: 2.1
Name: ibm-ai-openscale
Version: 2.2.1
Summary: Python SDK for IBM Watson OpenScale
Home-page: http://ai-openscale-python-client.mybluemix.net
Author: IBM
Author-email: lukasz.cmielowski@pl.ibm.com, maria.oleszkiewicz@pl.ibm.com, wojciech.sobala@pl.ibm.com
License: BSD
Keywords: AI,OpenScale,Watson,IBM,Bluemix,SDK,API,IBM Cloud,ICP,machine learning
Platform: UNKNOWN
Classifier: Development Status :: 5 - Production/Stable
Classifier: Natural Language :: English
Classifier: License :: OSI Approved :: Apache Software License
Classifier: Programming Language :: Python :: 3.5
Classifier: Programming Language :: Python :: 3.6
Classifier: Operating System :: MacOS :: MacOS X
Classifier: Operating System :: Microsoft :: Windows
Classifier: Operating System :: POSIX :: Linux
Classifier: Intended Audience :: Science/Research
Classifier: Intended Audience :: Developers
Classifier: Intended Audience :: Information Technology
Classifier: Topic :: Software Development :: Libraries
Classifier: Topic :: Software Development :: Libraries :: Python Modules
Classifier: Topic :: Scientific/Engineering :: Artificial Intelligence
Classifier: Topic :: Scientific/Engineering :: Information Analysis
Classifier: Topic :: Internet
Requires-Dist: requests
Requires-Dist: pandas
Requires-Dist: tabulate
Requires-Dist: h5py
